pybloomfilter.cpython-310-x86_64-linux-gnu.so
pybloomfiltermmap3py310-0.5.5.dist-info/RECORD
pybloomfiltermmap3py310-0.5.5.dist-info/top_level.txt
pybloomfiltermmap3py310-0.5.5.dist-info/AUTHORS
pybloomfiltermmap3py310-0.5.5.dist-info/LICENSE
pybloomfiltermmap3py310-0.5.5.dist-info/METADATA
pybloomfiltermmap3py310-0.5.5.dist-info/WHEEL
