Metadata-Version: 2.1
Name: pybloomfiltermmap3py310
Version: 0.5.5
Summary: A fast implementation of Bloom filter for Python 3 built on mmap
Home-page: https://github.com/prashnts/pybloomfiltermmap3
Author: Prashant Sinha
Author-email: prashant@noop.pw
License: MIT License
Classifier: Development Status :: 4 - Beta
Classifier: Intended Audience :: Developers
Classifier: Intended Audience :: Science/Research
Classifier: License :: OSI Approved :: MIT License
Classifier: Programming Language :: C
Classifier: Programming Language :: Cython
Classifier: Programming Language :: Python
Classifier: Programming Language :: Python :: 3
Classifier: Topic :: Software Development :: Libraries :: Python Modules
Requires-Python: >=3.5, <4
License-File: LICENSE
License-File: AUTHORS
